{
"meta":{"test_sets":[],"test_metrics":[],"learn_metrics":[{"best_value":"Min","name":"Logloss"}],"launch_mode":"Train","parameters":"","iteration_count":75,"learn_sets":["learn"],"name":"experiment"},
"iterations":[
{"learn":[0.6705124509],"iteration":0,"passed_time":0.00371388122,"remaining_time":0.2748272103},
{"learn":[0.6509579289],"iteration":1,"passed_time":0.007829235672,"remaining_time":0.285767102},
{"learn":[0.6364725986],"iteration":2,"passed_time":0.01302823593,"remaining_time":0.3126776622},
{"learn":[0.6189146975],"iteration":3,"passed_time":0.01778734541,"remaining_time":0.3157253811},
{"learn":[0.6033739303],"iteration":4,"passed_time":0.02252871731,"remaining_time":0.3154020423},
{"learn":[0.588203542],"iteration":5,"passed_time":0.02655727692,"remaining_time":0.3054086846},
{"learn":[0.5787522953],"iteration":6,"passed_time":0.03191264027,"remaining_time":0.3100085055},
{"learn":[0.5659903789],"iteration":7,"passed_time":0.03609927121,"remaining_time":0.3023313964},
{"learn":[0.5562199128],"iteration":8,"passed_time":0.04123892833,"remaining_time":0.3024188077},
{"learn":[0.5497187855],"iteration":9,"passed_time":0.04557012693,"remaining_time":0.296205825},
{"learn":[0.5430576649],"iteration":10,"passed_time":0.05131993395,"remaining_time":0.2985887066},
{"learn":[0.5374733301],"iteration":11,"passed_time":0.05531090772,"remaining_time":0.2903822655},
{"learn":[0.5304723817],"iteration":12,"passed_time":0.06029507745,"remaining_time":0.2875611386},
{"learn":[0.5252640126],"iteration":13,"passed_time":0.06484659641,"remaining_time":0.2825458843},
{"learn":[0.5195864215],"iteration":14,"passed_time":0.07009699304,"remaining_time":0.2803879721},
{"learn":[0.5140643622],"iteration":15,"passed_time":0.07429055544,"remaining_time":0.2739464232},
{"learn":[0.5094575763],"iteration":16,"passed_time":0.07981932276,"remaining_time":0.2723247482},
{"learn":[0.5058690115],"iteration":17,"passed_time":0.08429960966,"remaining_time":0.2669487639},
{"learn":[0.5014896449],"iteration":18,"passed_time":0.0897650112,"remaining_time":0.2645705593},
{"learn":[0.4974226921],"iteration":19,"passed_time":0.09432186992,"remaining_time":0.2593851423},
{"learn":[0.4950275345],"iteration":20,"passed_time":0.101913593,"remaining_time":0.2620635249},
{"learn":[0.4915654907],"iteration":21,"passed_time":0.1064933719,"remaining_time":0.2565522141},
{"learn":[0.4881361979],"iteration":22,"passed_time":0.1118233242,"remaining_time":0.2528179504},
{"learn":[0.4857876544],"iteration":23,"passed_time":0.1166426177,"remaining_time":0.2478655627},
{"learn":[0.4833854574],"iteration":24,"passed_time":0.1226774951,"remaining_time":0.2453549902},
{"learn":[0.4806126154],"iteration":25,"passed_time":0.1278758816,"remaining_time":0.2409968539},
{"learn":[0.4781214925],"iteration":26,"passed_time":0.1333796232,"remaining_time":0.2371193301},
{"learn":[0.4754530395],"iteration":27,"passed_time":0.1376403334,"remaining_time":0.231039131},
{"learn":[0.4735752196],"iteration":28,"passed_time":0.1436603325,"remaining_time":0.2278750102},
{"learn":[0.4710577168],"iteration":29,"passed_time":0.1481435781,"remaining_time":0.2222153672},
{"learn":[0.4692200735],"iteration":30,"passed_time":0.153564677,"remaining_time":0.2179627673},
{"learn":[0.4679396659],"iteration":31,"passed_time":0.1584077576,"remaining_time":0.2128604242},
{"learn":[0.4670303776],"iteration":32,"passed_time":0.1639098768,"remaining_time":0.2086125705},
{"learn":[0.4653909076],"iteration":33,"passed_time":0.1688364083,"remaining_time":0.2035968453},
{"learn":[0.4637474799],"iteration":34,"passed_time":0.174093196,"remaining_time":0.1989636526},
{"learn":[0.4626807975],"iteration":35,"passed_time":0.178669493,"remaining_time":0.1935586174},
{"learn":[0.461756324],"iteration":36,"passed_time":0.1841457527,"remaining_time":0.1891226649},
{"learn":[0.4608373431],"iteration":37,"passed_time":0.1886483821,"remaining_time":0.183683951},
{"learn":[0.4598976862],"iteration":38,"passed_time":0.1944551575,"remaining_time":0.1794970684},
{"learn":[0.4586857493],"iteration":39,"passed_time":0.1988756803,"remaining_time":0.1740162203},
{"learn":[0.4580908867],"iteration":40,"passed_time":0.2038730297,"remaining_time":0.1690654393},
{"learn":[0.457291626],"iteration":41,"passed_time":0.2081907967,"remaining_time":0.1635784831},
{"learn":[0.4561097639],"iteration":42,"passed_time":0.2132079558,"remaining_time":0.1586663857},
{"learn":[0.4551069283],"iteration":43,"passed_time":0.2171947656,"remaining_time":0.1530235849},
{"learn":[0.4541156517],"iteration":44,"passed_time":0.2225626304,"remaining_time":0.1483750869},
{"learn":[0.4527438199],"iteration":45,"passed_time":0.2265563038,"remaining_time":0.1428289741},
{"learn":[0.4519488926],"iteration":46,"passed_time":0.232075214,"remaining_time":0.1382575743},
{"learn":[0.4512247153],"iteration":47,"passed_time":0.2363431148,"remaining_time":0.1329430021},
{"learn":[0.4503569622],"iteration":48,"passed_time":0.2413943204,"remaining_time":0.1280867822},
{"learn":[0.449341088],"iteration":49,"passed_time":0.2457928181,"remaining_time":0.122896409},
{"learn":[0.4488576559],"iteration":50,"passed_time":0.2509125569,"remaining_time":0.1180764974},
{"learn":[0.4479345869],"iteration":51,"passed_time":0.2550401084,"remaining_time":0.1128062018},
{"learn":[0.4473742117],"iteration":52,"passed_time":0.2606662369,"remaining_time":0.1082010795},
{"learn":[0.446123817],"iteration":53,"passed_time":0.2646805232,"remaining_time":0.1029313146},
{"learn":[0.4453417011],"iteration":54,"passed_time":0.269752431,"remaining_time":0.09809179308},
{"learn":[0.4448995608],"iteration":55,"passed_time":0.2738083153,"remaining_time":0.09289924983},
{"learn":[0.4443739399],"iteration":56,"passed_time":0.2789770728,"remaining_time":0.08809802299},
{"learn":[0.4437961825],"iteration":57,"passed_time":0.2829017032,"remaining_time":0.08291946474},
{"learn":[0.4431835754],"iteration":58,"passed_time":0.2878912177,"remaining_time":0.07807219464},
{"learn":[0.4425005647],"iteration":59,"passed_time":0.292239453,"remaining_time":0.07305986326},
{"learn":[0.4414091997],"iteration":60,"passed_time":0.2973949177,"remaining_time":0.06825457129},
{"learn":[0.4409515302],"iteration":61,"passed_time":0.3014240278,"remaining_time":0.06320181227},
{"learn":[0.4402814012],"iteration":62,"passed_time":0.3068025854,"remaining_time":0.0584385877},
{"learn":[0.4395820826],"iteration":63,"passed_time":0.3113655477,"remaining_time":0.05351595351},
{"learn":[0.4390532653],"iteration":64,"passed_time":0.3167805866,"remaining_time":0.04873547486},
{"learn":[0.438765227],"iteration":65,"passed_time":0.3212985704,"remaining_time":0.04381344142},
{"learn":[0.4377910945],"iteration":66,"passed_time":0.3261113504,"remaining_time":0.03893866871},
{"learn":[0.4367554698],"iteration":67,"passed_time":0.330432396,"remaining_time":0.03401509959},
{"learn":[0.4362079355],"iteration":68,"passed_time":0.3363976351,"remaining_time":0.02925196827},
{"learn":[0.4352437083],"iteration":69,"passed_time":0.3410729932,"remaining_time":0.02436235665},
{"learn":[0.4347666429],"iteration":70,"passed_time":0.3467765445,"remaining_time":0.01953670673},
{"learn":[0.4344446275],"iteration":71,"passed_time":0.3509964842,"remaining_time":0.01462485351},
{"learn":[0.4337650737],"iteration":72,"passed_time":0.3567188567,"remaining_time":0.009773119361},
{"learn":[0.4330980579],"iteration":73,"passed_time":0.361038944,"remaining_time":0.004878904648},
{"learn":[0.4327501551],"iteration":74,"passed_time":0.3664174362,"remaining_time":0}
]}